{
  "name": "Ora French",
  "age": 29,
  "address": {
    "street": "Juzmi Trail",
    "city": "Tofecoj",
    "state": "NH",
    "zip": "07919"
  },
  "contact": {
    "phone": "(460) 383-7161",
    "servicePhone": "800734883"
  },
  "birthday": "1982-01-12T01:25:04.080Z",
  "ip": "236.173.146.106",
  "foo": "bar",
  "profile": {
    "about": "Kidiweade pafwatme ep afuin kuruwuv itpivve lugdoca nawu ageivhef degaf zeiz jod ec jolzahloc. Zibdo ewmam viozpav net fim sibi nozwum esgad zuro wabuhor ji utedutih zut du wu vakoj jajrani dov. Cebunom sokor jel ho vuvordun jad ibo uhu digikogi tezijses ace wevusoh zi pejse.",
    "bio": "Wa zukzacez deto gup ru ub as nokojes rujgesu jafpopi noces af viwes ozifuggul tihpehov cerju. Nojidkot pafab hatkuja edru cu bov gin lobniok timsa lageca cevam ijicaw. Jez tebwog usuvuco ezemeg mo ren ozlo omi ulizoz seti eteecwa iburit budhoina. Oge fitecefo nudsaf hikorjur deggaleh pakuoh ba lifac hewa iz kawib asle witamde ogoero pe rugom."
  },
  "apiKey": "20363784fd5fbf1ae8dfcb3383930d78a6cce00618dfb551a2532ad51fea596d",
  "currency": {
    "code": "RWF",
    "name": "Rwanda Franc"
  }
}