{
  "name": "Lucas Owens",
  "age": 39,
  "address": {
    "street": "Hupe Park",
    "city": "Habukevo",
    "state": "IA",
    "zip": "25808"
  },
  "contact": {
    "phone": "(984) 564-6411",
    "servicePhone": "800313211"
  },
  "birthday": "1996-02-16T11:16:08.774Z",
  "ip": "29.176.88.46",
  "foo": "bar",
  "profile": {
    "about": "Asitean pe fikpirwe eshejcoz bafuc bighok bur waehozug nukcioc domgijnu zan de kud. Vibud eduijifo bifbenol cozpoet me vilfimcag wofpavu amipekgu mebazac lihad ag dofifow. Da cim mejaz naulibil imu ojuma sejgapi cu bodum fen di deijte to dunaj urisenac koas jomuva. Muwko fazpa fatjak tegota vilitin limek uwemo in pig muj wihza atiamufa wavu wotmimrem ugo vuf pucvucma.",
    "bio": "Ziton degivug tobbofun wazesfe pocjitum gidap lig cevizi gufdu fezjupved icelumbi puumabek ah pa zodke an. Uvrug zalvu ava ruhzemvu luemiz dad hupujkow sizohge luwle okfifco carkufto tiv. Budgebila sep ce ran rolotdid cinijap ud gezo tidbalpu ezaza pafawmut naw. Pemres dufosit weppa cofri gaji coziwvet perate ku ubmu lojraf cetceono makiaka. Muw tosej kaza gija heb havcugbi hurjeif ehanepif ma rop cuvoer gavpa nusaj ezo fab mera norjihmi jeb."
  },
  "apiKey": "b067509a64de904f168df16494b2a6e946248e8727e86372ddd6178b58aa4515",
  "currency": {
    "code": "ARS",
    "name": "Argentina Peso"
  }
}